{"chunk_definitions":[{"row":34,"row_count":1,"visible":true,"expansion_state":0,"options":{"engine":"r","label":"Libraries","dev":"png"},"document_id":"28CD034F","chunk_id":"c0t3ksgr5ux5l","chunk_label":"Libraries"},{"row":115,"row_count":1,"visible":true,"expansion_state":0,"options":{"engine":"r","label":"Data Paths and Merging Data PLAY 1","dev":"png"},"document_id":"D2195E8D","chunk_id":"cxuzqqarziysu","chunk_label":"Data Paths and Merging Data PLAY 1"},{"row":150,"row_count":1,"visible":true,"expansion_state":0,"options":{"engine":"r","label":"Version number","dev":"png"},"document_id":"B91109C9","chunk_id":"cicaq512qg394","chunk_label":"Version number"},{"row":177,"row_count":1,"visible":true,"expansion_state":0,"options":{"engine":"r","label":"unnamed-chunk-1","dev":"png"},"document_id":"B91109C9","chunk_id":"ccgnz3gfycj9g","chunk_label":"6 Parameter Model"},{"row":214,"row_count":1,"visible":true,"expansion_state":0,"options":{"engine":"r","label":"unnamed-chunk-1","dev":"png"},"document_id":"B91109C9","chunk_id":"cq0oqvzsjx8sg","chunk_label":"unnamed-chunk-1"},{"row":329,"row_count":1,"visible":true,"expansion_state":0,"options":{"engine":"r","label":"unnamed-chunk-5","dev":"png"},"document_id":"B91109C9","chunk_id":"c0ng5ulnn2r6b","chunk_label":"unnamed-chunk-2"},{"row":629,"row_count":1,"visible":true,"expansion_state":0,"options":{"engine":"r","label":"Summarizing Parameters and Plotting","dev":"png"},"document_id":"B91109C9","chunk_id":"cucevs6thn375","chunk_label":"Summarizing Parameters and Plotting"},{"row":693,"row_count":1,"visible":true,"expansion_state":0,"options":{"engine":"r","label":"Diagnosis Split","dev":"png"},"document_id":"B91109C9","chunk_id":"cml3edids3qlz","chunk_label":"Diagnosis Split"},{"row":746,"row_count":1,"visible":true,"expansion_state":0,"options":{"engine":"r","label":"Correlations Between 6 Parameters and Symptoms","dev":"png"},"document_id":"B91109C9","chunk_id":"cx2lz0x5rmw2x","chunk_label":"Correlations Between 6 Parameters and Symptoms"},{"row":2159,"row_count":1,"visible":true,"expansion_state":0,"options":{"engine":"r","label":"Risky Choice Based on Future and Current - NextIsland only","dev":"png"},"document_id":"B91109C9","chunk_id":"c02b1adn4b8pd","chunk_label":"Risky Choice Based on Future and Current - NextIsland only"},{"row":4663,"row_count":1,"visible":true,"expansion_state":0,"options":{"engine":"r","label":"Risky Choices with NextIsland, Current Domain and Diagnosis Information Split by Anxiety Diagnosis","dev":"png"},"document_id":"B91109C9","chunk_id":"czzknjfsvw7yw","chunk_label":"Risky Choices with NextIsland"},{"row":4884,"row_count":1,"visible":true,"expansion_state":0,"options":{"engine":"r","label":"Depression Diagnosis, NextIsland","dev":"png"},"document_id":"B91109C9","chunk_id":"c1ebar6pg9x64","chunk_label":"Depression Diagnosis"},{"row":5484,"row_count":1,"visible":true,"expansion_state":0,"options":{"engine":"r","label":"unnamed-chunk-13","dev":"png"},"document_id":"D2195E8D","chunk_id":"cgdssk0woymvq","chunk_label":"unnamed-chunk-6"},{"row":5484,"row_count":1,"visible":true,"expansion_state":0,"options":{"engine":"r","label":"unnamed-chunk-13","dev":"png"},"document_id":"D2195E8D","chunk_id":"cgdssk0woymvq","chunk_label":"unnamed-chunk-6"},{"row":5616,"row_count":1,"visible":true,"expansion_state":0,"options":{"engine":"r","label":"Ver 1","dev":"png"},"document_id":"B91109C9","chunk_id":"c45duygqywcrs","chunk_label":"Version Number Plots"},{"row":5652,"row_count":1,"visible":true,"expansion_state":0,"options":{"engine":"r","label":"Happiness based on Version","dev":"png"},"document_id":"B91109C9","chunk_id":"cprijb26mulf3","chunk_label":"Happiness based on Version"},{"row":5681,"row_count":1,"visible":true,"expansion_state":0,"options":{"engine":"r","label":"unnamed-chunk-16","dev":"png"},"document_id":"B91109C9","chunk_id":"c4r5e3t6u23gk","chunk_label":"R2 Across Game Versions"},{"row":5708,"row_count":1,"visible":true,"expansion_state":0,"options":{"engine":"r","label":"Computing PastIsland","dev":"png"},"document_id":"B91109C9","chunk_id":"csk7dttxc19qj","chunk_label":"Computing PastIsland"},{"row":5780,"row_count":1,"visible":true,"expansion_state":0,"options":{"engine":"r","label":"% Risk-Taking based on PastIsland","dev":"png"},"document_id":"B91109C9","chunk_id":"cr3r4l4io4e65","chunk_label":"% Risk-Taking based on PastIsland"},{"row":5950,"row_count":1,"visible":true,"expansion_state":0,"options":{"engine":"r","label":"unnamed-chunk-9","dev":"png"},"document_id":"B91109C9","chunk_id":"cijxluooo7ssw","chunk_label":"unnamed-chunk-7"}],"doc_write_time":1729626774}